[
	{"drawDate": "03-01-2024", "one" : "08*26", "two" : "38*02", "three" : "13*09"},
	{"drawDate": "03-02-2024", "one" : "15*33", "two" : "40*36", "three" : "10*20"},
	{"drawDate": "03-03-2024", "one" : "09*19", "two" : "19*03", "three" : "24*25"},
	{"drawDate": "03-04-2024", "one" : "38*36", "two" : "25*31", "three" : "40*31"},
	{"drawDate": "03-05-2024", "one" : "29*40", "two" : "26*18", "three" : "35*14"},
	{"drawDate": "03-06-2024", "one" : "14*01", "two" : "11*15", "three" : "12*17"},
	{"drawDate": "03-07-2024", "one" : "12*28", "two" : "20*15", "three" : "03*19"},
	{"drawDate": "03-08-2024", "one" : "34*14", "two" : "39*16", "three" : "07*19"},
	{"drawDate": "03-09-2024", "one" : "16*33", "two" : "31*13", "three" : "19*13"},
	{"drawDate": "03-10-2024", "one" : "12*12", "two" : "17*34", "three" : "09*32"},
	{"drawDate": "03-11-2024", "one" : "17*08", "two" : "06*19", "three" : "05*31"},
	{"drawDate": "03-12-2024", "one" : "03*12", "two" : "23*31", "three" : "30*17"},
	{"drawDate": "03-13-2024", "one" : "16*10", "two" : "15*26", "three" : "04*22"},
	{"drawDate": "03-14-2024", "one" : "32*28", "two" : "36*39", "three" : "31*25"},
	{"drawDate": "03-15-2024", "one" : "32*29", "two" : "02*08", "three" : "02*40"},
	{"drawDate": "03-16-2024", "one" : "05*28", "two" : "13*14", "three" : "27*17"},
	{"drawDate": "03-17-2024", "one" : "09*33", "two" : "03*17", "three" : "32*15"},
	{"drawDate": "03-18-2024", "one" : "18*11", "two" : "37*11", "three" : "29*24"},
	{"drawDate": "03-19-2024", "one" : "08*21", "two" : "", "three" : ""}
]
